KNS_STT/__init__.py
kns_stt_package-0.1.dist-info/METADATA
kns_stt_package-0.1.dist-info/WHEEL
kns_stt_package-0.1.dist-info/top_level.txt
kns_stt_package-0.1.dist-info/RECORD
