Metadata-Version: 2.4
Name: KNS_STT_Package
Version: 0.1
Summary: My STT package. An Upgraded Version Of NetHyTech 0.1 Version 
Author: Author Name
Requires-Dist: selenium
Requires-Dist: webdriver-manager
Dynamic: author
Dynamic: requires-dist
Dynamic: summary
